Workbook

Sheet TUE FC Asset Plan SteerCo
A1: Fulfillment New Assets SteerCo (Tuesday's)
A3: Date | B3: Status | C3: Topic | D3: Mins | E3: PGM POC | F3: Lead(s) | G3: Required Attendees: | H3: Notes
A4: 45762 | B4: Completed | C4: Inform: Revised 5-yr Asset Plan and Capacity Deficits | D4: 20 | E4: Travis & Ellen | F4: Centroid: Hrishi/Neeraj | H4: Per alignment from Adam/Phil/CR
A5: 45762 | B5: Completed | C5: Post Audit results and next steps | D5: 20 | E5: Travis | F5: Finance: Matt T, PK S
A6: 45769 | B6: Completed | C6: Grey Orange | D6: 15 | E6: Ellen | F6: Xuejing Zhao
A7: 45776 | B7: Completed | C7: Final review of Post Audit deck; pre-V.S. 5/2 | D7: 15 | E7: Travis | F7: Matt T
A8: 45776 | B8: Completed | C8: Prelim Eng Design Sign-off for NG Southeast | D8: 20 | E8: Kourtney | F8: Lauren Siller
A9: 45776 | B9: Completed | C9: DFW3 / Grey Orange | D9: 15 | E9: Ellen | F9: Xuejing Z, Mike S
A10: 45776 | B10: Completed | C10: Final Review of NextGen SE Proposal deck for DD | D10: 30 | E10: Kourtney | F10: Various | H10: Move to 5/1 Next Gen SteerCo
A11: 45776 | B11: Completed | C11: Non-Sort Purchase Strategy | D11: 15 | E11: Jess, Ellen | F11: Centroid: Rohit Singhal
A12: 45776 | B12: Completed | C12: DFW5/PHL5 Checklist & Resource Coverage | D12: 10 | E12: Liz | F12: Mike Spigoda
A13: 45783 | B13: Completed | C13: Revised 5 yr Asset Plan and Capacity Deficits Follow-up: Non-sort summary + overal network next steps/game plan | D13: 30 | E13: Travis & Ellen | F13: Centroid: Hrishi/Rohit | H13: Not covered 4.22 due to time overrun. Pushing to next week. Per 4/23 convo with Hrishi; can target 5/6 Mtg for combined sort/non-sort review + next steps
A14: 45783 | B14: Completed | C14: Update: Fulfillment Portfolio Prioritization "MVP" | D14: 30 | E14: Liz | F14: Travis, Ellen | H14: Share initial view per request last week; discuss next steps
A15: 45783 | B15: Completed | C15: Non-Sort CLT2 Engineering Design 30% Sign Off | D15: 20 | E15: Jess Stahl
A16: 45783 | B16: Completed | C16: IND1 (2-tier + ICC) Engineering Design | D16: 40 | E16: Kanistha
A17: 45804 | B17: Completed | C17: Decide: Prioritization Next Steps | D17: 20 | E17: Travis | F17: Team
A18: 45804 | B18: Completed | C18: Decide: NE & W BDR Sign-off | D18: 20 | E18: Kourtney | F18: Hrishi, Neeraj | H18: Moved from prior meetings; need to complete. Discussed 5/27, did not finalize.
A19: 45804 | B19: Completed | C19: Discuss: 2-Tier Business Case and Product LOE | D19: 30 | E19: Ellen | F19: Phoebe F, Manny R | G19: Alex R, Ron J, + | H19: Provide update post alignment from Ops, Centroid, and Finance
A20: 45818 | B20: Completed | C20: Decide: NE & W BDR Sign-off | D20: 20 | E20: Kourtney | F20: Hrishi, Neeraj | G20: Adam, Vik, CR, Phil, Jacob | H20: Receieved approval sign-off with Ops offline approval
A21: 45818 | B21: Completed | C21: Discuss/Decide: Approach to accelerate pre-buy request to fast-follow RECC DD request | D21: 30 | E21: Kourtney | F21: Kourtney | G21: Adam, Vik, CR, Phil, Jacob | H21: Partially Discussed: Moved to 6/17 for decsion
A22: 45825 | B22: Completed | C22: Energy Efficiency Projects | D22: 30 | E22: Travis & Ellen | F22: Rachel Paulk | G22: Adam, Vik, CR, Phil, Jacob | H22: Planning for VS on 6/20, then SC DB/Eng SteerCo TBD
A23: 45825 | B23: Off | C23: SE Next Gen 30% Design Review | D23: 30 | E23: Kourtney | F23: Nicole B | G23: Adam, Vik, CR, Phil, Jacob | H23: (Inform to KS on 6/20)
A24: 45825 | B24: Completed | C24: Discuss/Decide: Approach to accelerate pre-buy request to fast-follow REC DD request | D24: 30 | E24: Kourtney | F24: Kourtney | G24: Adam, Vik, CR, Phil, Jacob | H24: Approved to move forward to CPC and ASM without 30% design
A25: 45825 | B25: Completed | C25: Inform: IND1 + Non Sort Governance Timelines | D25: 0 | E25: Ellen Sloneker | F25: Ellen Sloneker
A26: 45832 | B26: Completed | C26: Next Gen SE Full Review: DD & Prebuy REC to ASM | D26: 60 | E26: Kourtney | F26: Multiple | G26: Adam, Vik, CR, Phil, Jacob
A27: 45832 | B27: Completed | C27: Review Non-Sort and IND1 (2-tier + ICC) CPC Deck | D27: 30 | E27: Ellen Sloneker | F27: Multiple | G27: Adam, Vik, CR, Phil, Jacob, Ameya, Hrishi
A28: 45847 | B28: Completed | C28: IND1 - Two-Tier + ICC Symbotic Engineering Design - Preliminary Review _ Sign Off | D28: 20 | E28: Kanistha Coombs | F28: Joaquin Diaz Martin | G28: Ada Dunbar, Mike Spigoda Karen Slatton
A29: 45847 | B29: Completed | C29: West Next Gen: Site Selection | D29: 20 | E29: Kourtney | G29: Ada Dunbar, Mike Spigoda Karen Slatton | H29: Vantage was approved to move forward to Karisa
A30: 45847 | B30: Completed | C30: SMF2 - Budget Deep Dive and Ad Hoc Requests | D30: 30 | E30: Liz Glenn | F30: Multiple | G30: Ada Dunbar, Mike Spigoda Karen Slatton
A31: 45853 | B31: Completed | C31: SMF2 Budget Review | D31: 30 | E31: Liz Glenn | F31: Liz | G31: Adam, Vik, CR, Phil, Jacob | H31: Follow up from 7/11.
A32: 45881 | B32: TBD | C32: Decide: NE, W, & SE: DD Prebuy, and Land Bank Proposal approval prior to VS Review | D32: 75 | E32: Kourtney | F32: Kourtney
A33: 45888 | B33: Completed | C33: SMF2 Budget Update August | D33: 15 | E33: Liz | F33: Liz G | G33: Adam, Vik, CR, Phil, Jacob, Brian | H33: Inform : Status of all active projects budgets. Follow up on SMF2 open actions
A34: 45895 | B34: Completed | C34: Decide: IND1 2Tier Operations and Review | D34: 40 | E34: Kanistha | F34: Joaquin | G34: Adam, Vik, CR, Phil, Jacob
A35: 45874 | B35: Completed | C35: Inform: NE Site Selection - Risk | D35: 30 | E35: Kourtney | F35: Allison | G35: Adam, Vik, CR, Phil, Jacob, Brian | H35: Going to VS on 8/8
A36: 45874 | B36: Completed | C36: Inform: West Site Section- Risk | D36: 30 | E36: Kourtney | F36: Allison | G36: Adam, Vik, CR, Phil, Jacob, Brian | H36: Going to VS on 8/8
A37: 45874 | B37: Completed | C37: Review: SE Next Gen CPC Feedback Review | D37: 60 | E37: Kourtney | F37: Nicole B | G37: Adam, Vik, CR, Phil, Jacob, Brian
A38: 45855 | B38: Completed | C38: ORD1 Mezzanine Follow-up | D38: 15 | E38: Liz Glenn | F38: Tabitha M / MaryEllen K | G38: Adam, Vik, Jacob, ...
A39: 9.2.2025 | B39: Scheduled | C39: Decide: Site Selection NE NonSort(Hartford, CT and Central PA. Align: FY29 + FY30 Non-Sort Asset Strategy | D39: 45 | E39: Ellen Sloneker | F39: Rodrigo, Allison , Joaquin | G39: Adam, Vik, CR, Phil, Jacob, Brian, Bradon Massey | H39: Going to VS on 8/8
A40: 7/29/2025 Move to 7/30 | B40: Completed | C40: Discuss: NE/W Status - Discuss risks to plan and align on expectations | D40: 30 | E40: Kourtney | F40: Kourtney | G40: VPs | H40: This was Pre-read only
A41: 7/29/2025 Move to 7/30 | B41: Completed | C41: Decide: SE NG 30% Design Buidling Infrastructure | D41: 30 | E41: Kourtney | F41: Nicole B | G41: Adam, Vik, CR, Phil, Jacob, Brian | H41: Building Infrastructure – 65’ Clear, Building Size for Offline Area, Mezzanine Pre-Build for Flexibility IP Assumptions to Enable Handoff to Construction
A42: 7/29/2025 Move to 7/30 | B42: Completed | C42: Decide: IP BDR Sign-off | D42: 30 | E42: Ellen | F42: Vijay | G42: Adam, Vik, CR, Phil, Jacob, Brian | H42: Decide: BRD Leadership Sign-off going to VS 8/8
A43: 45883 | B43: Completed | C43: SMF2 Next Gen Totes | D43: 20 | E43: Liz | F43: Mahil and David D | G43: Adam, Vik, CR, Phil, Jacob, Brian | H43: Review the tote selection for SMF2
A44: 9.2.2025 | B44: Scheduled | C44: Update: SE Next Gen - White Paper/PPT Update | D44: 45 | E44: Kourtney | F44: Kourtney | G44: Adam, Vik, CR, Phil, Jacob, Brian
A45: TBD | B45: TBD | C45: Decide: DFW5/PHL5 BDR sign-off | D45: 20 | E45: Liz | F45: Neeraj, Pradeep | G45: Adam, Vik, CR, Phil, Jacob | H45: BDR provided to Eng on 4/21. Eng has stopped review due to direction; if directed to restart will need ~1-1.5 weeks for Eng review and then ~1 week for Cen revisions.
A46: TBD | B46: TBD | C46: Inform: Peak Shaving Follow-up | D46: 30 | E46: N/A | F46: Adam, Hrishi, Vik | G46: Jack A, (Merch?) | H46: Dropped from 5/27 per Hrishi
A47: 45909 | B47: Completed | C47: Decide: West Site Selection | D47: 30 | E47: Kourtney | F47: Kourtney | G47: Adam, Vik
A48: 45916 | B48: Scheduled | C48: Decide: NG Norheast and West Prelim Eng Design Sign-off | D48: 30 | E48: Kourtney | F48: Nicole B | G48: Adam, Vik, CR, Phil, Jacob, Brian
A49: 45916 | B49: Scheduled | C49: Decide: NG Nov Capital Cycle Approval | D49: 60 | E49: Kourtney | F49: Team | G49: Adam, Vik, CR, Phil, Jacob, Brian
A50: 45923 | B50: Scheduled | C50: Decide: Non-Sort || BDL DD + Central PA Site Selection | D50: 20 | E50: Ellen Sloneker | H50: VS on 9/26
A51: 45923 | B51: Scheduled | C51: Decide: LAX2 ICC Expansion FY27 | D51: 20 | E51: Kanistha Coombs | F51: Team | G51: Vik, Phil, Adam, Ameya, Akash, Joaquin, MaryEllen, Kyle Caryle | H51: VS on 9/26 a) Review design and operational modifications within LAX2 to partially support LRP need for next year b) Review options recommended (with associated pros and cons of each option) to help bridge the capacity need for FY27 and FY28 c) Future roadmap for ICCs needed based on current LRP projections.
A52: 45923 | B52: Scheduled | C52: Inform: IND1 2 Tier Decision Board Pre-Review | D52: 30 | E52: Kanistha Coombs | F52: Team | G52: Vik, Phil, Adam, Ameya, Akash, Joaquin, MaryEllen | H52: VS on 9/26 Review updated deck with Karisa'a feedback on: a) a clear outline of the process flow through the current engineering design b) updated business case outlining how seller fees are being subsidised
A53: 45923 | B53: Scheduled | C53: Decide: Next Gen SE Land Purchase and Design Fees | D53: 30 | E53: Kourtney Miller | F53: Team | G53: Vik, Phil, Adam, Ameya, Akash, Joaquin, MaryEllen | H53: VS on 9/26
A54: 45930 | B54: Scheduled | C54: Decide: LAX2 ICC Expansion FY27 | D54: 30 | E54: Kanistha Coombs | F54: Joaquin Diaz Martin, Alayah Silas, Manny Rodriguez | G54: Vik, Phil, Adam, Hrishi | H54: Review updates on engineering design from 9/23 Asset SteerCo
A55: 45937 | B55: Scheduled | C55: PHL5/DFW5 Buisness Case Discussion | D55: 30 | E55: Liz Glenn | F55: Nicole B, Neerja, Luke P | G55: Vik, Phil, Adam, Hrishi | H55: Discuss the PHL5/DFW5 buisness case and next steps
A56: 45930 | C56: Decide: DFW5/PHL5 Path Forward | D56: 15 | E56: Liz Glenn | F56: Nicole Blyth, Dave Hall | G56: Mike Spigoda, Phil, Adam, Hrishi, Jacob Shub, Dave Hall | H56: What needs to be true to hit a December governance timeline and FY27 pre-peak go live.
A57: 45930 | C57: Align: Supply Chain Decision board feedback and next steps (NextGen + IND1-Two Tier + ICC) | D57: 20 | E57: Kanistha Coombs and Kourtney Miller | F57: Joaquin Diaz Martin, Nicole Blyth, Manny Rodriguez | G57: Mike Spigoda, Phil, Adam, Hrishi, Jacob Shub, Barat Smith, Mitch Fevold | H57: Debrief and align next steps following SCDB
A58: 45937 | B58: Scheduled | C58: Non-Sort Optimization | D58: 30 | E58: Scott Smith | G58: Vik, Phil, Adam, Hrishi
A59: 45937 | B59: Scheduled | C59: LAX2 ICC Expansion | D59: 30 | E59: Kanistha Coombs
A60: 45944 | B60: Scheduled | C60: IND1 FAQ Review | D60: 30 | E60: Kanistha Coombs | F60: Hrishi, Fede, Noah, Manny, Mo, Vamsi | G60: Vik, Phil, Jacob, Alex, Adam
A61: 45944 | B61: Scheduled | C61: NE & W CapEx | D61: 30 | E61: Kourtney Miller | F61: Nicole B, Kodi, Neeraj, Allison, Zach | G61: Adam, Vik, CR, Phil, Jacob, Brian
A62: 45951 | B62: Scheduled | C62: DFW5/PHL5 Expansions | D62: Pre-Read | E62: Liz Glenn | F62: Luke Pullock/Nicole B | H62: Buisness case update
A63: 45951 | B63: Scheduled | C63: SMF2 Yard Truck | D63: 10 | E63: Maryellen /Liz Glenn | F63: Adam, Barat
A64: 45958 | B64: Scheduled | C64: NE & W CapEx | D64: 15 | E64: Kourtney Miller | F64: Nicole B, Kodi, Neeraj, Allison, Zach | G64: Adam, Mike S, CR, Phil, Jacob, Karen
A65: 45951 | B65: Tentative | C65: LAX2 Design Sign off | D65: 30 | E65: Kanistha Coombs | F65: Noah | G65: Adam, Vik, CR, Phil, Jacob, Brian
A66: 45951 | B66: Scheduled | C66: IP Design 60% Sign off | D66: 30 | E66: Ellen | F66: Nicole B | G66: Adam, Vik, CR, Phil, Jacob, Brian
A67: 45951 | B67: Scheduled | C67: Non-Sort Asset FY29/FY30 - BDL, CVG, Central PA (x2) | D67: 30 | E67: Ellen Sloneker
A68: 45958 | B68: Scheduled | C68: DFW5/PHL5 Expansions | D68: 25 | E68: Liz Glenn | F68: Nicole B & Luke Polluck | G68: Adam,Mike, CR, Phil, Jacob, Karen
A69: 45951 | B69: Scheduled | C69: Pre-Read PHX2 90% | D69: Pre-Read | E69: Scott Smith | F69: Wil Elshoff, Scott Smith | G69: Adam, Vik, CR, Phil, Jacob, Brian
A70: 45958 | B70: Scheduled | C70: WFS RC Intergration | D70: 25 | E70: Scott Smith | F70: Scott Smith, Aditya Afle, Christy Olsen, Bucky Bailess | G70: Adam, Sylvester, Phil, Jacob, Karen
A71: 45958 | B71: Scheduled | C71: LAX2 Design Sign off | D71: 25 | E71: Kanistha Coombs | F71: Noah Jackson & Mike Spigoda | G71: Adam, Mike S, CR, Phil, Jacob, Karen
A72: 45965 | B72: Complete | C72: LAX2 Strategy and BC Review | D72: 25 | E72: Kanistha Coombs | F72: Federico Laino, Manny Rodriguez cc: Akash Agrawal | G72: Adam, Mike S., Phil, Jacob
A73: 45965 | B73: Complete | C73: LAX Standalone ICC BDR Review | D73: 25 | E73: Kanistha Coombs | F73: Federico Laino, Hrishi Badve | G73: Adam, CR, Phil
A74: 45972 | B74: Scheduled | C74: DFW5/ PHL5 Expansions - DD Fund ask + 60% design sign off | D74: 30 | E74: Liz Glenn | F74: Liz Glenn | G74: Adam, Mike S., Phil, Jacob | H74: Automation Counsel 11/13
A75: 45965 | B75: Complete | C75: BRD and ENG Concept Design FY29 Nonsort CVG2, PHL6, BDL1 | D75: 40 | E75: Ellen | F75: Akkshit, Joaquin Diaz | G75: Adam, Mike S., Phil, Jacob
A76: 45972 | B76: Scheduled | C76: SMF2 Budget Update- PreRead Only | D76: 0 | E76: Liz Glenn | F76: Liz , Kodi
A77: 45972 | B77: Scheduled | C77: FL9 Lease Renewal | D77: 20 | E77: Ellen Sloneker | F77: Allison Coontz, Manny Rodriguez, Loren Beightol
A78: 45972 | B78: Scheduled | C78: LAX2 Budget + Strategy | D78: 40 | E78: Kanistha
A79: 45979 | B79: Scheduled | C79: Pre-Read FL9 Lease Renewal | D79: 0 | E79: Ellen | F79: -- | G79: --
A80: 45986 | B80: Scheduled | C80: PHL1 IP Phase 2 Design | D80: 30 | E80: Nicole Blythe | F80: Nicole Blythe | G80: Adam Dunbar, Mike Spigoda, Karen Slatton, Phil Herr, Jacob Shub
A81: 45979 | B81: Scheduled | C81: New Next Gen (Closed Session) | D81: 30 | E81: Kourtney Miller | F81: Kourtney Miller | G81: Adam Dunbar, Mike Spigoda, Karen Slatton, Phil Herr, Jacob Shub , PK, Brandon
A82: 45993 | B82: Completed | C82: LAX1 Sorter | D82: 30 | E82: Ellen Sloneker
A83: TBD | B83: Not Scheduled | C83: Non-Sort EV Yard Truck Review | D83: 15 | E83: Scott Smith | F83: Scott Smith, Wil Elshoff, Devin Pitts | G83: Adam Dunbar, Mike Spigoda, Karen Slatton, Phil Herr, Dave Hall
A84: 46007 | B84: Scheduled | C84: Atlas Roadmap Discusson : Closed Session | D84: 30 | E84: Meghan
A85: 46000 | B85: Complete | C85: Peak Pop Up Discussion | D85: 30 | E85: Liz Glenn
A86: 46028 | B86: Scheduled | C86: Expansions : RRF Funds Review | D86: 30 | E86: Liz Glenn | F86: Luke
A87: 46000 | B87: Complete | C87: SMF2 Budget | D87: 15 | E87: Liz Glenn
A88: 46000 | B88: Complete | C88: LAX2 ICC Expansion : CPC Preview | D88: 10 | E88: Kanistha | G88: Adam Dunbar, Mike Spigoda, Karen Slatton, Phil Herr, Jacob Shub
A89: 46007 | B89: Scheduled | C89: NE & W CapEx Pulse Check (Closed Session) | D89: 60 | E89: Kourtney Miller | F89: Andrew & Kodi | G89: Adam Dunbar, Mike Spigoda, Karen Slatton, Phil Herr, Jacob Shub
A90: 45663 | B90: Scheduled | C90: Peak Pop Up SCDB | D90: 30 | E90: Liz Glenn | H90: SCDB on 1/12
A91: 46007 | B91: Scheduled | C91: IND1 Opertaionl Update | D91: 60 | E91: Kanistha
B397: *-

Sheet NG Scheduling
A1: WW | B1: Program | C1: Status | D1: Forum | E1: Governance Date | F1: Topic | G1: Turn-in WW | H1: Turn-in Date | I1: Turn-in Time | J1: Mins | K1: Presenter | L1: Submitter | M1: Purpose | N1: Decision & Outcome | O1: Presentation Link | P1: Decision Owners & Approvers | AI1: WW Turn-in Date
A2: FY26 | B2: NextGen | C2: Complete | D2: SteerCo | E2: 46044 | F2: Douglas PSA | G2: =A2 -> FY26 | H2: =E2-1 -> 46043 | I2: 0.625 | J2: 30 | K2: Kourtney Miller | L2: Kourtney Miller | M2: Not Approved | N2: Stop due diligence for Douglas
A3: FY26 | B3: NextGen | C3: Complete | D3: SteerCo | E3: 46044 | F3: Las Vegas Land Bank | G3: =A3 -> FY26 | H3: =E3-1 -> 46043 | I3: 0.625 | J3: 30 | K3: Kourtney Miller | L3: Kourtney Miller | M3: Approved | AI3: =H3 -> 46043
A4: FY26 | B4: NextGen | C4: Complete | D4: SteerCo | E4: 46044 | F4: Pivot from Las Vegas to Phoenix | G4: =A4 -> FY26 | H4: =E4-1 -> 46043 | I4: 0.625 | J4: 30 | K4: Kourtney Miller | L4: Kourtney Miller | M4: Approved | N4: Aligned to Pivot to Phoenix | AI4: =H4 -> 46043
A5: FY26 | B5: NextGen | C5: Complete | D5: Vertical Start-up | E5: 46045 | F5: Pivot from Las Vegas to Phoenix | G5: =A5 -> FY26 | H5: =E5-1 -> 46044 | I5: 0.625 | J5: 30 | K5: Vijay Manoharan | L5: Kourtney Miller | M5: Inform | N5: Aligned to Pivot to Phoenix | AI5: =H5 -> 46044
A6: =IF(ISBLANK(E6),"",_xlfn.XLOOKUP(E6,Info!A:A,Info!B:B)) -> #N/A | B6: NextGen | C6: Complete | D6: NextGen SteerCo | E6: 46051 | F6: Spec Building Analysis for Northeast | G6: =IF(ISBLANK(H6),"",_xlfn.XLOOKUP(H6,Info!A:A,Info!B:B)) -> #N/A | H6: =E6-1 -> 46050 | I6: 0.66666667 | J6: 30 | K6: Nicole Blythe | L6: Nicole Byth | M6: Decide | N6: Not approved to move forward with Spec Building | O6: 26_01_29 Northeast Spec Bld Analysis.pptx | P6: Adam Dunbar, Vik Gopalakrishnan, Jack Anderson, Jacob Shub | AI6: =H6 -> 46050
A7: =IF(ISBLANK(E7),"",_xlfn.XLOOKUP(E7,Info!A:A,Info!B:B)) -> 1 | B7: NextGen | C7: Complete | D7: Mechanisms | E7: 46056 | F7: $1M DD for MCO, SEA, DEN, MSP | G7: =IF(ISBLANK(H7),"",_xlfn.XLOOKUP(H7,Info!A:A,Info!B:B)) -> 1 | H7: =E7-1 -> 46055 | I7: 0.625 | J7: 30 | K7: Ellen Sloneker | L7: Kourtney Miller | M7: Not Improved | N7: Rob's wants a review of the Depot and NextGen Ecosystem | AI7: =H7 -> 46055
A8: =IF(ISBLANK(E8),"",_xlfn.XLOOKUP(E8,Info!A:A,Info!B:B)) -> 1 | B8: NextGen | C8: Complete | D8: Mechanisms | E8: 46056 | F8: 30-60% DD Request REC request for Wallkill and Buckeye | G8: =IF(ISBLANK(H8),"",_xlfn.XLOOKUP(H8,Info!A:A,Info!B:B)) -> 1 | H8: =E8-1 -> 46055 | I8: 0.625 | J8: 30 | K8: Ellen Sloneker | L8: Kourtney Miller | M8: Not Improved | N8: Rob's wants a review of the Depot and NextGen Ecosystem | AI8: =H8 -> 46055
A9: =IF(ISBLANK(E9),"",_xlfn.XLOOKUP(E9,Info!A:A,Info!B:B)) -> 1 | B9: NextGen | C9: Complete | D9: Mechanisms | E9: 46056 | F9: Las Vegas Land Bank | G9: =IF(ISBLANK(H9),"",_xlfn.XLOOKUP(H9,Info!A:A,Info!B:B)) -> 1 | H9: =E9-1 -> 46055 | I9: 0.625 | J9: 30 | K9: Ellen Sloneker | L9: Kourtney Miller | M9: Move Forward | AI9: =H9 -> 46055
A10: =IF(ISBLANK(E10),"",_xlfn.XLOOKUP(E10,Info!A:A,Info!B:B)) -> 1 | B10: NextGen | C10: Complete | D10: Mechanisms | E10: 46056 | F10: Pivot from Las Vegas to Phoenix | G10: =IF(ISBLANK(H10),"",_xlfn.XLOOKUP(H10,Info!A:A,Info!B:B)) -> 1 | H10: =E10-1 -> 46055 | I10: 0.625 | J10: 30 | K10: Ellen Sloneker | L10: Kourtney Miller | M10: Approved | N10: Aligned to Pivot to Phoenix | AI10: =H10 -> 46055
A11: =IF(ISBLANK(E11),"",_xlfn.XLOOKUP(E11,Info!A:A,Info!B:B)) -> 3 | B11: NextGen | C11: Complete | D11: SteerCo | E11: 46073 | F11: Carnesville CapEx Reduction - MHE Value Engineering | G11: =IF(ISBLANK(H11),"",_xlfn.XLOOKUP(H11,Info!A:A,Info!B:B)) -> 3 | H11: =E11-1 -> 46072 | I11: 0.625 | J11: 30 | K11: Nicole Blythe | L11: Kourtney Miller | M11: Approved | N11: Approve to implement VE for all NextGen's | AI11: =H11 -> 46072
A12: =IF(ISBLANK(E12),"",_xlfn.XLOOKUP(E12,Info!A:A,Info!B:B)) -> 3 | B12: NextGen | C12: Complete | D12: SteerCo | E12: 46073 | F12: Sortable SKU Definition < 1.6 to 1.2 | G12: =IF(ISBLANK(H12),"",_xlfn.XLOOKUP(H12,Info!A:A,Info!B:B)) -> 3 | H12: =E12-1 -> 46072 | I12: 0.625 | J12: 30 | K12: Nicole Blythe | L12: Kourtney Miller | M12: Not Approved | N12: Pause active work for 1.2 Units Cube | O12: 26_02_20 Carnesville CapEx Reduction Slides-SteerCo.pdf | AI12: =H12 -> 46072
A13: =IF(ISBLANK(E13),"",_xlfn.XLOOKUP(E13,Info!A:A,Info!B:B)) -> 4 | B13: NextGen | C13: Complete | D13: SteerCo | E13: 46079 | F13: Carnesville Business Case | G13: =IF(ISBLANK(H13),"",_xlfn.XLOOKUP(H13,Info!A:A,Info!B:B)) -> 4 | H13: =E13-1 -> 46078 | I13: 0.625 | J13: 30 | K13: Matt Termeer | L13: Kourtney Miller | M13: Inform | AI13: =H13 -> 46078
A14: =IF(ISBLANK(E14),"",_xlfn.XLOOKUP(E14,Info!A:A,Info!B:B)) -> 4 | B14: NextGen | C14: Complete | D14: SteerCo | E14: 46079 | F14: EV Yard Trucks | G14: =IF(ISBLANK(H14),"",_xlfn.XLOOKUP(H14,Info!A:A,Info!B:B)) -> 4 | H14: =E14-1 -> 46078 | I14: 0.625 | J14: 30 | K14: Brook Weeks | L14: Kourtney Miller | M14: Approved | O14: 26_02_26 SteerCo Carnesville BC_IP Increase Yard Trucks.pptx | AI14: =H14 -> 46078
A15: =IF(ISBLANK(E15),"",_xlfn.XLOOKUP(E15,Info!A:A,Info!B:B)) -> 4 | B15: NextGen | C15: Complete | D15: SteerCo | E15: 46079 | F15: Increase IP from 60% to 80% | G15: =IF(ISBLANK(H15),"",_xlfn.XLOOKUP(H15,Info!A:A,Info!B:B)) -> 4 | H15: =E15-1 -> 46078 | I15: 0.625 | J15: 30 | K15: Hrishi Badve | L15: Kourtney Miller | M15: Approved | O15: 26_02_26 SteerCo Carnesville BC_IP Increase Yard Trucks.pptx | AI15: =H15 -> 46078
A16: =IF(ISBLANK(E16),"",_xlfn.XLOOKUP(E16,Info!A:A,Info!B:B)) -> 4 | B16: NextGen | C16: Complete | D16: Rob's 1:1 w/Kieran | E16: 46080 | F16: 30-60% DD Request REC request for Wallkill and Buckeye | G16: =IF(ISBLANK(H16),"",_xlfn.XLOOKUP(H16,Info!A:A,Info!B:B)) -> 4 | H16: =E16-1 -> 46079 | I16: 0.625 | J16: 30 | K16: Ellen Sloneker | L16: Ellen Sloneker | M16: Approved | AI16: =H16 -> 46079
A17: =IF(ISBLANK(E17),"",_xlfn.XLOOKUP(E17,Info!A:A,Info!B:B)) -> 4 | B17: NextGen | C17: Complete | D17: Rob's 1:1 w/Kieran | E17: 46080 | F17: NextGen vs Depot Strategy | G17: =IF(ISBLANK(H17),"",_xlfn.XLOOKUP(H17,Info!A:A,Info!B:B)) -> 4 | H17: =E17-1 -> 46079 | I17: 0.625 | J17: 30 | K17: Jack Anderson | L17: Ellen Sloneker | M17: Aligned | AI17: =H17 -> 46079
A18: =IF(ISBLANK(E18),"",_xlfn.XLOOKUP(E18,Info!A:A,Info!B:B)) -> 5 | B18: NextGen | C18: Complete | D18: SteerCo | E18: 46083 | F18: Buckeye Site Selection | G18: =IF(ISBLANK(H18),"",_xlfn.XLOOKUP(H18,Info!A:A,Info!B:B)) -> 5 | H18: =E18-1 -> 46082 | I18: 0.625 | J18: 30 | K18: Allison Coontz | L18: Kourtney Miller | M18: Move Forward | AI18: =H18 -> 46082
A19: =IF(ISBLANK(E19),"",_xlfn.XLOOKUP(E19,Info!A:A,Info!B:B)) -> 5 | B19: NextGen | C19: Complete | D19: Vertical Start-up | E19: 46083 | F19: Buckeye Site Selection | G19: =IF(ISBLANK(H19),"",_xlfn.XLOOKUP(H19,Info!A:A,Info!B:B)) -> 5 | H19: =E19-1 -> 46082 | I19: 0.625 | J19: 30 | K19: Allison Coontz | L19: Kourtney Miller | M19: No | AI19: =H19 -> 46082
A20: =IF(ISBLANK(E20),"",_xlfn.XLOOKUP(E20,Info!A:A,Info!B:B)) -> 5 | B20: NextGen | C20: Complete | D20: SteerCo | E20: 46086 | F20: Impact to Increase in IP Increase | G20: =IF(ISBLANK(H20),"",_xlfn.XLOOKUP(H20,Info!A:A,Info!B:B)) -> 5 | H20: =E20-1 -> 46085 | I20: 0.625 | J20: 30 | K20: Nicole Blythe | L20: Kourtney Miller | M20: Inform | O20: 26_03_05 SteerCo IP Moved to 80%_Wallkill Political Update & Business Case.pptx | AI20: =H20 -> 46085
A21: =IF(ISBLANK(E21),"",_xlfn.XLOOKUP(E21,Info!A:A,Info!B:B)) -> 5 | B21: NextGen | C21: Complete | D21: SteerCo | E21: 46086 | F21: IP Increase Impact to Business Case | G21: =IF(ISBLANK(H21),"",_xlfn.XLOOKUP(H21,Info!A:A,Info!B:B)) -> 5 | H21: =E21-1 -> 46085 | I21: 0.625 | J21: 30 | K21: Matt Termeer | L21: Kourtney Miller | M21: Inform | N21: Approve to implement VE for all NextGen's | O21: 26_03_05 SteerCo IP Moved to 80%_Wallkill Political Update & Business Case.pptx | AI21: =H21 -> 46085
A22: =IF(ISBLANK(E22),"",_xlfn.XLOOKUP(E22,Info!A:A,Info!B:B)) -> 5 | B22: NextGen | C22: Complete | D22: SteerCo | E22: 46086 | F22: IP Limit | G22: =IF(ISBLANK(H22),"",_xlfn.XLOOKUP(H22,Info!A:A,Info!B:B)) -> 5 | H22: =E22-1 -> 46085 | I22: 0.625 | J22: 30 | K22: Hrishi Badve | L22: Kourtney Miller | M22: Inform | O22: 26_03_05 SteerCo IP Moved to 80%_Wallkill Political Update & Business Case.pptx
A23: =IF(ISBLANK(E23),"",_xlfn.XLOOKUP(E23,Info!A:A,Info!B:B)) -> 5 | B23: NextGen | C23: Complete | D23: SteerCo | E23: 46086 | F23: Wallkill Pollical Headwinds | G23: =IF(ISBLANK(H23),"",_xlfn.XLOOKUP(H23,Info!A:A,Info!B:B)) -> 5 | H23: =E23-1 -> 46085 | I23: 0.625 | J23: 30 | K23: Kourtney Miller | L23: Kourtney Miller | M23: Inform | O23: 26_03_05 SteerCo IP Moved to 80%_Wallkill Political Update & Business Case.pptx
A24: =IF(ISBLANK(E24),"",_xlfn.XLOOKUP(E24,Info!A:A,Info!B:B)) -> 6 | B24: NextGen | C24: Complete | D24: SteerCo | E24: 46093 | F24: Buckeye BDR Sign-off | G24: =IF(ISBLANK(H24),"",_xlfn.XLOOKUP(H24,Info!A:A,Info!B:B)) -> 6 | H24: =E24-1 -> 46092 | I24: 0.625 | J24: 30 | K24: Hrishi Badve | L24: Kourtney Miller | M24: Not Approved | N24: Additional follow-up Required | O24: 26_03_12 SteerCo.pptx
A25: =IF(ISBLANK(E25),"",_xlfn.XLOOKUP(E25,Info!A:A,Info!B:B)) -> 6 | B25: NextGen | C25: Complete | D25: SteerCo | E25: 46093 | F25: Carnesville Business Case Inputs | G25: =IF(ISBLANK(H25),"",_xlfn.XLOOKUP(H25,Info!A:A,Info!B:B)) -> 6 | H25: =E25-1 -> 46092 | I25: 0.625 | J25: 30 | K25: Matt Termeer | L25: Kourtney Miller | M25: Inform | O25: 26_03_12 SteerCo.pptx
A26: =IF(ISBLANK(E26),"",_xlfn.XLOOKUP(E26,Info!A:A,Info!B:B)) -> 6 | B26: NextGen | C26: Complete | D26: SteerCo | E26: 46093 | F26: Carnesville May ASM Content Alignment | G26: =IF(ISBLANK(H26),"",_xlfn.XLOOKUP(H26,Info!A:A,Info!B:B)) -> 6 | H26: =E26-1 -> 46092 | I26: 0.625 | J26: 30 | K26: Kourtney Miller | L26: Kourtney Miller | M26: Inform | O26: 26_03_12 SteerCo.pptx
A27: =IF(ISBLANK(E27),"",_xlfn.XLOOKUP(E27,Info!A:A,Info!B:B)) -> 6 | B27: NextGen | C27: Complete | D27: SteerCo | E27: 46093 | F27: Increasing Energy CapEx by $5.1M | G27: =IF(ISBLANK(H27),"",_xlfn.XLOOKUP(H27,Info!A:A,Info!B:B)) -> 6 | H27: =E27-1 -> 46092 | I27: 0.625 | J27: 30 | K27: Zach Freeze | L27: Kourtney Miller | M27: Approved | N27: Approved Increase CapEx for Energy | O27: 26_03_12 SteerCo Energy CapEx Increase.pptx
A28: =IF(ISBLANK(E28),"",_xlfn.XLOOKUP(E28,Info!A:A,Info!B:B)) -> 7 | B28: NextGen | C28: Complete | D28: SteerCo | E28: 46100 | F28: Buckeye BDR Sign-off | G28: =IF(ISBLANK(H28),"",_xlfn.XLOOKUP(H28,Info!A:A,Info!B:B)) -> 7 | H28: =E28-1 -> 46099 | I28: 0.625 | J28: 30 | K28: Vijay Manoharan | L28: Kourtney Miller | M28: Approved | N28: Buckeye BDR Approved | O28: 26_03_19 SteerCo BDR Buckeye & Wallkill_ Wallkill Timeline.pptx
A29: =IF(ISBLANK(E29),"",_xlfn.XLOOKUP(E29,Info!A:A,Info!B:B)) -> 7 | B29: NextGen | C29: Complete | D29: Vertical Start-up | E29: 46100 | F29: Carnesville Full Capital Ask | G29: =IF(ISBLANK(H29),"",_xlfn.XLOOKUP(H29,Info!A:A,Info!B:B)) -> 7 | H29: =E29-1 -> 46099 | I29: 0.625 | J29: 30 | K29: Team | L29: Kourtney Miller | M29: Decision
A30: =IF(ISBLANK(E30),"",_xlfn.XLOOKUP(E30,Info!A:A,Info!B:B)) -> 7 | B30: NextGen | C30: Complete | D30: SteerCo | E30: 46100 | F30: Wallkill BDR Sign-off | G30: =IF(ISBLANK(H30),"",_xlfn.XLOOKUP(H30,Info!A:A,Info!B:B)) -> 7 | H30: =E30-1 -> 46099 | I30: 0.625 | J30: 30 | K30: Vijay Manoharan | L30: Kourtney Miller | M30: Approved | N30: Wallkill BRR Approved | O30: 26_03_19 SteerCo BDR Buckeye & Wallkill_ Wallkill Timeline.pptx
A31: =IF(ISBLANK(E31),"",_xlfn.XLOOKUP(E31,Info!A:A,Info!B:B)) -> 7 | B31: NextGen | C31: Complete | D31: SteerCo | E31: 46100 | F31: Wallkill Timeline push from Nov FY30 to May FY31 | G31: =IF(ISBLANK(H31),"",_xlfn.XLOOKUP(H31,Info!A:A,Info!B:B)) -> 7 | H31: =E31-1 -> 46099 | I31: 0.625 | J31: 30 | K31: Karen Slatton | L31: Kourtney Miller | M31: Approved | O31: 26_03_19 SteerCo BDR Buckeye & Wallkill_ Wallkill Timeline.pptx
A32: =IF(ISBLANK(E32),"",_xlfn.XLOOKUP(E32,Info!A:A,Info!B:B)) -> 9 | B32: NextGen | C32: Complete | D32: FOX | E32: 46114 | F32: Fulfillment Ecosystem | G32: =IF(ISBLANK(H32),"",_xlfn.XLOOKUP(H32,Info!A:A,Info!B:B)) -> 9 | H32: =E32-1 -> 46113 | I32: 0.625 | J32: 60 | K32: Jack Anderson, Adam Dunbar | M32: Inform | N32: Carnesville Pre-socialization | O32: Carnesville May ASM | P32: Leah Platz, Kyle Carlyle, Mike Walden
A33: =IF(ISBLANK(E33),"",_xlfn.XLOOKUP(E33,Info!A:A,Info!B:B)) -> 9 | B33: NextGen | C33: Complete | D33: Vertical Start-up | E33: 46114 | F33: Wallkill Business Case | G33: =IF(ISBLANK(H33),"",_xlfn.XLOOKUP(H33,Info!A:A,Info!B:B)) -> 9 | H33: 46113 | I33: 0.5 | J33: 15 | K33: Matt Termeer | L33: Matt Termeer | M33: Inform | O33: Wallkill VS Update | P33: Karisa Sprague, Adam Dunbar, Barat Smith
A34: =IF(ISBLANK(E34),"",_xlfn.XLOOKUP(E34,Info!A:A,Info!B:B)) -> 9 | B34: NextGen | C34: Complete | D34: Vertical Start-up | E34: 46114 | F34: Wallkill Business Case | G34: =IF(ISBLANK(H34),"",_xlfn.XLOOKUP(H34,Info!A:A,Info!B:B)) -> 9 | H34: =E34-1 -> 46113 | I34: 0.625 | J34: 30 | K34: Matt Termeer | L34: Kourtney Miller | M34: Inform
A35: =IF(ISBLANK(E35),"",_xlfn.XLOOKUP(E35,Info!A:A,Info!B:B)) -> 9 | B35: NextGen | C35: Complete | D35: Vertical Start-up | E35: 46114 | F35: Wallkill Go Live date push from Nov to May | G35: =IF(ISBLANK(H35),"",_xlfn.XLOOKUP(H35,Info!A:A,Info!B:B)) -> 9 | H35: =E35-1 -> 46113 | I35: 0.625 | J35: 30 | K35: Kodi Pratt | L35: Kourtney Miller | M35: Inform
A36: =IF(ISBLANK(E36),"",_xlfn.XLOOKUP(E36,Info!A:A,Info!B:B)) -> 9 | B36: NextGen | C36: Complete | D36: Vertical Start-up | E36: 46114 | F36: Wallkill Status Update | G36: =IF(ISBLANK(H36),"",_xlfn.XLOOKUP(H36,Info!A:A,Info!B:B)) -> 9 | H36: 46113 | I36: 0.5 | J36: 15 | K36: Kodi Pratt | L36: Kodi Pratt | M36: Inform | O36: Wallkill VS Update | P36: Greg Nunn, Jason Klipa
A37: =IF(ISBLANK(E37),"",_xlfn.XLOOKUP(E37,Info!A:A,Info!B:B)) -> 9 | B37: NextGen | C37: Complete | D37: Vertical Start-up | E37: 46114 | F37: Wallkill status update with pollical risk | G37: =IF(ISBLANK(H37),"",_xlfn.XLOOKUP(H37,Info!A:A,Info!B:B)) -> 9 | H37: =E37-1 -> 46113 | I37: 0.625 | J37: 30 | K37: Kodi Pratt | L37: Kourtney Miller | M37: Inform
A38: =IF(ISBLANK(E38),"",_xlfn.XLOOKUP(E38,Info!A:A,Info!B:B)) -> 9 | B38: NextGen | C38: Complete | D38: Vertical Start-up | E38: 46114 | F38: Wallkill Timeline Update | G38: =IF(ISBLANK(H38),"",_xlfn.XLOOKUP(H38,Info!A:A,Info!B:B)) -> 9 | H38: 46113 | I38: 0.5 | J38: 15 | K38: Kodi Pratt | L38: Kodi Pratt | M38: Inform | O38: Wallkill VS Update | P38: Greg Nunn, Jason Klipa
A39: =IF(ISBLANK(E39),"",_xlfn.XLOOKUP(E39,Info!A:A,Info!B:B)) -> 9 | B39: NextGen | C39: Complete | D39: SteerCo | E39: 46115 | F39: Adding Project Antelope to Carnesville Business Case | G39: =IF(ISBLANK(H39),"",_xlfn.XLOOKUP(H39,Info!A:A,Info!B:B)) -> 9 | H39: =E39-1 -> 46114 | I39: 0.625 | J39: 30 | K39: Nicole Blythe | L39: Kourtney Miller | M39: Approved | N39: Approved to adding Project Antelope to all NextGen Business Cases | O39: 26_04_02 SteerCo Cost to Server Carnesville Maintenance Strategy.pptx
A40: =IF(ISBLANK(E40),"",_xlfn.XLOOKUP(E40,Info!A:A,Info!B:B)) -> 9 | B40: NextGen | C40: Complete | D40: NextGen SteerCo | E40: 46115 | F40: Carnesville Maintenance Strategy | G40: =IF(ISBLANK(H40),"",_xlfn.XLOOKUP(H40,Info!A:A,Info!B:B)) -> 9 | H40: 46114 | I40: 0.625 | J40: 15 | K40: Nicole Byth | L40: Nicole Byth | M40: Decide | N40: Add Project Antelope to Carnesville Business Case | O40: SteerCo 4/3 | P40: Kelly Boyle, Micah Baldwin, Joel Beckwith, Fred Gulley
A41: =IF(ISBLANK(E41),"",_xlfn.XLOOKUP(E41,Info!A:A,Info!B:B)) -> 9 | B41: NextGen | C41: Complete | D41: SteerCo | E41: 46115 | F41: Cost to Serve Alignment | G41: =IF(ISBLANK(H41),"",_xlfn.XLOOKUP(H41,Info!A:A,Info!B:B)) -> 9 | H41: =E41-1 -> 46114 | I41: 0.625 | J41: 30 | K41: Nicole Blythe | L41: Kourtney Miller | M41: Approved | N41: Proceed with Option 1 | O41: 26_04_02 SteerCo Cost to Server Carnesville Maintenance Strategy.pptx
A42: =IF(ISBLANK(E42),"",_xlfn.XLOOKUP(E42,Info!A:A,Info!B:B)) -> 9 | B42: NextGen | C42: Complete | D42: NextGen SteerCo | E42: 46115 | F42: Cost to Server | G42: =IF(ISBLANK(H42),"",_xlfn.XLOOKUP(H42,Info!A:A,Info!B:B)) -> 9 | H42: 46114 | I42: 0.625 | J42: 15 | K42: Nicole Byth | L42: Nicole Byth | M42: Discuss | O42: SteerCo 4/4
A43: =IF(ISBLANK(E43),"",_xlfn.XLOOKUP(E43,Info!A:A,Info!B:B)) -> 9 | B43: NextGen | C43: Complete | D43: Offline | E43: 46115 | F43: REC Dry Run | G43: =IF(ISBLANK(H43),"",_xlfn.XLOOKUP(H43,Info!A:A,Info!B:B)) -> 9 | H43: 46115 | I43: N/A | J43: 60 | K43: Ellen Sloneker | L43: Kourtney Miller | M43: Prepare | O43: Carnesville May ASM | P43: Karisa Sprague, Adam Dunbar, Barat Smith
A44: =IF(ISBLANK(E44),"",_xlfn.XLOOKUP(E44,Info!A:A,Info!B:B)) -> 10 | B44: NextGen | C44: Complete | D44: Mechanisms | E44: 46119 | F44: DD for MCO, MSP, DEN, SEA | G44: =IF(ISBLANK(H44),"",_xlfn.XLOOKUP(H44,Info!A:A,Info!B:B)) -> 10 | H44: 46118 | I44: 0.5 | K44: Ellen Sloneker | L44: Ellen Sloneker | M44: Decide | O44: Rob Mechanism Update
A45: =IF(ISBLANK(E45),"",_xlfn.XLOOKUP(E45,Info!A:A,Info!B:B)) -> 10 | B45: NextGen | C45: Complete | D45: Offline | E45: 46119 | F45: Fulfillment Ecosystem, Cost, & Value Engineering w/ Rob Montgomery | G45: =IF(ISBLANK(H45),"",_xlfn.XLOOKUP(H45,Info!A:A,Info!B:B)) -> 10 | H45: =E45-1 -> 46118 | I45: 0.625 | J45: 60 | K45: Jack Anderson, Karisa Sprague, Adam Dunbar | M45: Inform | N45: Carnesville Pre-socialization | O45: Carnesville May ASM | P45: Rob Montgomery
A46: =IF(ISBLANK(E46),"",_xlfn.XLOOKUP(E46,Info!A:A,Info!B:B)) -> 10 | B46: NextGen | C46: Complete | D46: Offline | E46: 46121 | F46: REC Dry Run | G46: =IF(ISBLANK(H46),"",_xlfn.XLOOKUP(H46,Info!A:A,Info!B:B)) -> 10 | H46: 46120 | I46: N/A | J46: 60 | K46: Ellen Sloneker | L46: Kourtney Miller | M46: Prepare | O46: Carnesville May ASM | P46: Karisa Sprague, Adam Dunbar, Barat Smith
A47: =IF(ISBLANK(E47),"",_xlfn.XLOOKUP(E47,Info!A:A,Info!B:B)) -> 10 | B47: NextGen | C47: Complete | D47: NextGen SteerCo | E47: 46121 | F47: Socialization Strategy | G47: =IF(ISBLANK(H47),"",_xlfn.XLOOKUP(H47,Info!A:A,Info!B:B)) -> 10 | H47: 46120 | I47: 0.625 | J47: 30 | K47: Kourtney Miller | L47: Kourtney Miller | M47: Prepare | O47: SteerCo 4/9
A48: =IF(ISBLANK(E48),"",_xlfn.XLOOKUP(E48,Info!A:A,Info!B:B)) -> 10 | B48: NextGen | C48: Complete | D48: Rob's 1:1 w/Kieran | E48: 46122 | F48: Carnesville Full Capital Ask | G48: =IF(ISBLANK(H48),"",_xlfn.XLOOKUP(H48,Info!A:A,Info!B:B)) -> 10 | H48: 46121 | I48: 0.5 | J48: 30 | K48: Adam Dunbar | L48: Kourtney Miller | M48: Decide | N48: Full approval for Carnesville | O48: Carnesville May ASM | P48: This was cancelled since the meeting was moved post REC
A49: =IF(ISBLANK(E49),"",_xlfn.XLOOKUP(E49,Info!A:A,Info!B:B)) -> 11 | B49: NextGen | C49: Complete | D49: Offline | E49: 46125 | F49: Carnesville Pre-socialization + MSM / Julie Barber | G49: =IF(ISBLANK(H49),"",_xlfn.XLOOKUP(H49,Info!A:A,Info!B:B)) -> 11 | H49: =E49-1 -> 46124 | I49: 0.625 | J49: 60 | K49: Jack Anderson, Karisa Sprague, Adam Dunbar, Leah Platz | M49: Inform | N49: Carnesville Pre-socialization | O49: Carnesville May ASM | P49: Julie Barber
A50: =IF(ISBLANK(E50),"",_xlfn.XLOOKUP(E50,Info!A:A,Info!B:B)) -> 11 | B50: NextGen | C50: Complete | D50: SteerCo | E50: 46125 | F50: NextGen + Non-sort Campus Approach (MCO, MSP, DEN, SEA) | G50: =IF(ISBLANK(H50),"",_xlfn.XLOOKUP(H50,Info!A:A,Info!B:B)) -> 11 | H50: 46125 | I50: 0.5 | J50: 40 | K50: Kourtney Miller | L50: Kourtney Miller | M50: Decide | N50: Requirements for Campus | O50: 26_04_13 SteerCo NG & NS Campus.pptx | P50: Adam Dunbar, Vik Gopalakrishnan, Jack Anderson, John Clinton
A51: =IF(ISBLANK(E51),"",_xlfn.XLOOKUP(E51,Info!A:A,Info!B:B)) -> 11 | B51: NextGen | C51: Complete | D51: REC | E51: 46127 | F51: Carnesville Full Capital Ask | G51: =IF(ISBLANK(H51),"",_xlfn.XLOOKUP(H51,Info!A:A,Info!B:B)) -> 10 | H51: 46122 | I51: 0.625 | J51: 30 | K51: Karisa Sprague | L51: Kourtney Miller | M51: Approved | N51: Move forward to CPC | O51: Carnesville May ASM | P51: Rob Montgomery, Karisa Sprague, Adam Dunbar, Vik Gopalakrishnan, Jack Anderson, John Clinton, PK Sabherwal, Matt Termeer, Nicole Blyth, Ellen Sloneker, Karen Slatton
A52: =IF(ISBLANK(E52),"",_xlfn.XLOOKUP(E52,Info!A:A,Info!B:B)) -> 11 | B52: NextGen | C52: Complete | D52: NextGen SteerCo | E52: 46129 | F52: BDR for MCO | G52: =IF(ISBLANK(H52),"",_xlfn.XLOOKUP(H52,Info!A:A,Info!B:B)) -> 11 | H52: =E52-1 -> 46128 | I52: 0.625 | J52: 30 | K52: Vijay Manoharan | L52: Vijay Manoharan | M52: Approved | N52: BDR Approved for MCO | O52: SteerCo 4/17 | P52: Adam Dunbar, Vik Gopalakrishnan, Jack Anderson, John Clinton
A53: =IF(ISBLANK(E53),"",_xlfn.XLOOKUP(E53,Info!A:A,Info!B:B)) -> 11 | B53: NextGen | C53: Complete | D53: NextGen SteerCo | E53: 46129 | F53: Buckeye: Transportation & Solar Land Requirements | G53: =IF(ISBLANK(H53),"",_xlfn.XLOOKUP(H53,Info!A:A,Info!B:B)) -> 11 | H53: =E53-1 -> 46128 | I53: 0.625 | J53: 30 | K53: Ary Neuwirth & Logan Jones | L53: Ary Neuwirth & Logan Jones | M53: Follow-up | N53: Need Rob's feedback. Follow up required | O53: SteerCo 4/17 | P53: Alesha Murcia, Ary Neuwirth, Zack Freeze
A54: =IF(ISBLANK(E54),"",_xlfn.XLOOKUP(E54,Info!A:A,Info!B:B)) -> 12 | B54: NextGen | C54: Complete | D54: Offline | E54: 46133 | F54: Carnesville Pre-socialization / Tim Skinner | G54: =IF(ISBLANK(H54),"",_xlfn.XLOOKUP(H54,Info!A:A,Info!B:B)) -> 12 | H54: =E54-1 -> 46132 | I54: 0.625 | J54: 60 | K54: Jack Anderson, Karisa Sprague, Adam Dunbar, Mike Walden | M54: Inform | N54: Carnesville Pre-socialization | O54: Carnesville May ASM | P54: Tim Skinner
A55: =IF(ISBLANK(E55),"",_xlfn.XLOOKUP(E55,Info!A:A,Info!B:B)) -> 12 | B55: NextGen | C55: Complete | D55: Offline | E55: 46133 | F55: Carnesville Pre-socialization + MSM / Dave Guggina | G55: =IF(ISBLANK(H55),"",_xlfn.XLOOKUP(H55,Info!A:A,Info!B:B)) -> 12 | H55: =E55-1 -> 46132 | I55: 0.5 | J55: 30 | K55: Adam Dunbar | L55: Kourtney Miller | M55: Inform | N55: Pre-CPC feedback | O55: Carnesville May ASM | P55: Dave Guggina, Karisa Sprague, Adam Dunbar, Jacob Shub, John Clinton, Vik Gopalakrishnan, Ellen Sloneker
A56: =IF(ISBLANK(E56),"",_xlfn.XLOOKUP(E56,Info!A:A,Info!B:B)) -> 12 | B56: NextGen | C56: Complete | D56: NextGen SteerCo | E56: 46135 | F56: BDR for MSP, DEN, SEA | G56: =IF(ISBLANK(H56),"",_xlfn.XLOOKUP(H56,Info!A:A,Info!B:B)) -> 12 | H56: =E56-1 -> 46134 | I56: 0.625 | J56: 30 | K56: Vijay Manoharan | L56: Vijay Manoharan | M56: Decide | N56: Not approved - Scheduling follow up | O56: SteerCo 4/23 | P56: Adam Dunbar, Vik Gopalakrishnan, Jack Anderson, John Clinton
A57: =IF(ISBLANK(E57),"",_xlfn.XLOOKUP(E57,Info!A:A,Info!B:B)) -> 12 | B57: NextGen | C57: Complete | D57: Offline | E57: 46135 | F57: Carnesville Pre-socialization + MSM w/ Seth Dallaire & Manish Joneja | G57: =IF(ISBLANK(H57),"",_xlfn.XLOOKUP(H57,Info!A:A,Info!B:B)) -> 12 | H57: =E57-1 -> 46134 | I57: 0.625 | J57: 60 | K57: Jack Anderson, Karisa Sprague, Adam Dunbar, Kyle Carlyle | M57: Inform | N57: Carnesville Pre-socialization | O57: Carnesville May ASM | P57: Seth Dallaire & Manish Joneja
A58: =IF(ISBLANK(E58),"",_xlfn.XLOOKUP(E58,Info!A:A,Info!B:B)) -> 12 | B58: NextGen | C58: Complete | D58: SteerCo | E58: 46135 | F58: Follow up Buckeye: Transportation & Solar Land Requirements | G58: =IF(ISBLANK(H58),"",_xlfn.XLOOKUP(H58,Info!A:A,Info!B:B)) -> 12 | H58: =E58-1 -> 46134 | I58: 0.66666667 | J58: 15 | K58: Ary Neuwirth & Logan Jones | L58: Ary Neuwirth & Logan Jones | M58: Decide | N58: Approved | O58: SteerCo 4/23
A59: =IF(ISBLANK(E59),"",_xlfn.XLOOKUP(E59,Info!A:A,Info!B:B)) -> 12 | B59: NextGen | C59: Complete | D59: Offline | E59: 46136 | F59: Buckeye Transportation Land Requirements w/ Rob Montgomery | G59: =IF(ISBLANK(H59),"",_xlfn.XLOOKUP(H59,Info!A:A,Info!B:B)) -> 12 | H59: 46135 | I59: 0.66666667 | J59: 60 | K59: Ellen Sloneker | L59: Ellen Sloneker | M59: Decide | N59: Pursue all 63 areas for Buckeye | O59: 26_04_24 Buckeye Land Purchase Alignment.pptx | P59: Rob Montgomery and Ryan McDaniels
A60: =IF(ISBLANK(E60),"",_xlfn.XLOOKUP(E60,Info!A:A,Info!B:B)) -> 13 | B60: NextGen | C60: Complete | D60: Offline | E60: 46139 | F60: Carnesville Pre-socialization + MSM / Todd Sears | G60: =IF(ISBLANK(H60),"",_xlfn.XLOOKUP(H60,Info!A:A,Info!B:B)) -> 13 | H60: =E60-1 -> 46138 | I60: 0.625 | J60: 60 | K60: Rob Montgomery, John Clinton, PK Sabherwal, Matt Termeer | M60: Inform | N60: Carnesville Pre-socialization | O60: Carnesville May ASM | P60: Todd Sears
A61: =IF(ISBLANK(E61),"",_xlfn.XLOOKUP(E61,Info!A:A,Info!B:B)) -> 13 | B61: NextGen | C61: Complete | D61: SteerCo | E61: 46139 | F61: Wallkill Business Case Inputs - Action to Improve IRR | G61: =IF(ISBLANK(H61),"",_xlfn.XLOOKUP(H61,Info!A:A,Info!B:B)) -> 12 | H61: 46136 | I61: 0.66666667 | J61: 60 | K61: Kourtney Miller | L61: Kourtney Miller | M61: Inform | O61: 26_04_27 Wallkill IRR Deep Dive.pptx | P61: Adam Dunbar, Vik Gopalakrishnan, Jack Anderson, John Clinton
A62: =IF(ISBLANK(E62),"",_xlfn.XLOOKUP(E62,Info!A:A,Info!B:B)) -> 13 | B62: NextGen | C62: Complete | D62: NextGen SteerCo | E62: 46142 | F62: Burn Testing for NextGen | G62: =IF(ISBLANK(H62),"",_xlfn.XLOOKUP(H62,Info!A:A,Info!B:B)) -> 13 | H62: =E62-1 -> 46141 | I62: 0.66666667 | J62: 15 | K62: Kodi Pratt | L62: Kodi Pratt | M62: Decide | N62: Approved. Matt Termeer finding funding | O62: 26_04_30 SteerCo.pptx | P62: Adam Dunbar, Vik Gopalakrishnan, Jack Anderson, John Clinton
A63: =IF(ISBLANK(E63),"",_xlfn.XLOOKUP(E63,Info!A:A,Info!B:B)) -> 13 | B63: NextGen | C63: Complete | D63: NextGen SteerCo | E63: 46142 | F63: Wallkill Business Case | G63: =IF(ISBLANK(H63),"",_xlfn.XLOOKUP(H63,Info!A:A,Info!B:B)) -> 13 | H63: =E63-1 -> 46141 | I63: 0.16666667 | J63: 45 | K63: Kourtney Miller | L63: Kourtney Miller | M63: Inform | O63: 26_04_30 SteerCo.pptx | P63: Adam Dunbar, Vik Gopalakrishnan, Jack Anderson, John Clinton
A64: =IF(ISBLANK(E64),"",_xlfn.XLOOKUP(E64,Info!A:A,Info!B:B)) -> 13 | B64: NextGen | C64: Complete | D64: NextGen SteerCo | E64: 46143 | F64: Carnesville MSM Dry Run | G64: =IF(ISBLANK(H64),"",_xlfn.XLOOKUP(H64,Info!A:A,Info!B:B)) -> 13 | H64: =E64-2 -> 46141 | I64: 0.66666667 | J64: 60 | K64: Karisa Sprague | L64: Kourtney Miller | M64: Prepare | O64: Carnesville May ASM | P64: Karisa Sprague, Adam Dunbar, John Clinton
A65: =IF(ISBLANK(E65),"",_xlfn.XLOOKUP(E65,Info!A:A,Info!B:B)) -> 13 | B65: NextGen | C65: Complete | D65: Offline | E65: 46143 | F65: Carnesville Pre-socialization + MSM w/ Tracy Poulliot , Camilo Canedo, Dan Fleming | G65: =IF(ISBLANK(H65),"",_xlfn.XLOOKUP(H65,Info!A:A,Info!B:B)) -> 13 | H65: =E65-1 -> 46142 | I65: 0.625 | J65: 60 | K65: Jack Anderson, Karisa Sprague, Adam Dunbar, Mike Walden | M65: Inform | N65: Carnesville Pre-socialization | O65: Carnesville May ASM | P65: Tracy Poulliot , Camilo Canedo, Dan Fleming
A66: =IF(ISBLANK(E66),"",_xlfn.XLOOKUP(E66,Info!A:A,Info!B:B)) -> 14 | B66: NextGen | C66: Complete | D66: CFO Review | E66: 46146 | F66: Carnesville Full Capital Ask | G66: =IF(ISBLANK(H66),"",_xlfn.XLOOKUP(H66,Info!A:A,Info!B:B)) -> 13 | H66: 46139 | I66: 0.5 | J66: 30 | K66: John Clinton, PK Sabherwal, Matt Termeer | L66: Kourtney Miller | M66: Decide | N66: Full approval for Carnesville | O66: Carnesville May ASM | P66: Todd Sears
A67: =IF(ISBLANK(E67),"",_xlfn.XLOOKUP(E67,Info!A:A,Info!B:B)) -> 14 | B67: NextGen | C67: Complete | D67: NextGen SteerCo | E67: 46146 | F67: Solar location for Buckeye | G67: =IF(ISBLANK(H67),"",_xlfn.XLOOKUP(H67,Info!A:A,Info!B:B)) -> 13 | H67: 46143 | I67: 0.16666667 | J67: 20 | K67: Logan Jones | L67: Kourtney Miller | M67: Decide | N67: Approved: Option 1 Carport + Zone 3 | O67: 26_05_04 SteerCo.pptx | P67: Adam Dunbar, Barat Smith, Zach Freeze, Karen Slatton
A68: =IF(ISBLANK(E68),"",_xlfn.XLOOKUP(E68,Info!A:A,Info!B:B)) -> 14 | B68: NextGen | C68: Complete | D68: NextGen SteerCo | E68: 46146 | F68: Van Delivery Requirements / Flow | G68: =IF(ISBLANK(H68),"",_xlfn.XLOOKUP(H68,Info!A:A,Info!B:B)) -> 13 | H68: 46143 | I68: 0.66666667 | J68: 20 | K68: Advaith Venkataraman | L68: Advaith Venkataraman | M68: Decide | N68: Need follow up | O68: 26_05_04 SteerCo.pptx | P68: Adam Dunbar, Vik Gopalakrishnan, Jack Anderson, John Clinton
A69: =IF(ISBLANK(E69),"",_xlfn.XLOOKUP(E69,Info!A:A,Info!B:B)) -> 14 | B69: NextGen | C69: Complete | D69: NextGen SteerCo | E69: 46146 | F69: Wallkill Next Steps | G69: =IF(ISBLANK(H69),"",_xlfn.XLOOKUP(H69,Info!A:A,Info!B:B)) -> 13 | H69: 46143 | I69: 0.66666667 | J69: 20 | K69: Kourtney Miller | L69: Kourtney Miller | M69: Decide | O69: 26_05_04 SteerCo.pptx
A70: =IF(ISBLANK(E70),"",_xlfn.XLOOKUP(E70,Info!A:A,Info!B:B)) -> 14 | B70: NextGen | C70: Complete | D70: Offline | E70: 46147 | F70: Carnesville Pre-socialization w/ Latriece Watkins & Tom Ward | G70: =IF(ISBLANK(H70),"",_xlfn.XLOOKUP(H70,Info!A:A,Info!B:B)) -> 14 | H70: =E70-1 -> 46146 | I70: 0.625 | J70: 60 | K70: Rob Montgomery, Jack Anderson, Karisa Spraque, Adam Dunbar, Matt C | M70: Inform | N70: Carnesville Pre-socialization | O70: Carnesville May ASM | P70: Latriece Watkins & Tom Ward
A71: =IF(ISBLANK(E71),"",_xlfn.XLOOKUP(E71,Info!A:A,Info!B:B)) -> 14 | B71: NextGen | C71: Complete | D71: NextGen SteerCo | E71: 46150 | F71: Wallkill IRR & CapEx | G71: =IF(ISBLANK(H71),"",_xlfn.XLOOKUP(H71,Info!A:A,Info!B:B)) -> 14 | H71: =E71-1 -> 46149 | I71: 0.66666667 | J71: 45 | K71: Kourtney Miller | L71: Kourtney Miller | M71: Decide | N71: Focus on Building Options (1) ORD Style, (2) BDL (3) Reduced footprint maintain 2M SKU | O71: 26_05_08 SteerCo.pptx
A72: =IF(ISBLANK(E72),"",_xlfn.XLOOKUP(E72,Info!A:A,Info!B:B)) -> 15 | B72: NextGen | C72: Complete | D72: MSM | E72: 46154 | F72: Carnesville Full Capital Ask | G72: =IF(ISBLANK(H72),"",_xlfn.XLOOKUP(H72,Info!A:A,Info!B:B)) -> 14 | H72: 46147 | I72: 0.5 | J72: 30 | K72: Karisa Sprague | L72: Kourtney Miller | M72: Decide | N72: Approved to move to ASM | O72: Carnesville May ASM | P72: Dave Guggina
A73: =IF(ISBLANK(E73),"",_xlfn.XLOOKUP(E73,Info!A:A,Info!B:B)) -> 15 | B73: NextGen | C73: Complete | D73: NextGen SteerCo | E73: 46156 | F73: Wallkill IRR & CapEx (Building Scenario's) | G73: =IF(ISBLANK(H73),"",_xlfn.XLOOKUP(H73,Info!A:A,Info!B:B)) -> 15 | H73: =E73-1 -> 46155 | I73: 0.16666667 | J73: 60 | K73: Nicole Blyth | L73: Nicole Byth | M73: Inform | O73: 26_05_14 SteerCo.pptx | P73: Adam Dunbar, Vik Gopalakrishnan, Jack Anderson, John Clinton
A74: =IF(ISBLANK(E74),"",_xlfn.XLOOKUP(E74,Info!A:A,Info!B:B)) -> 16 | B74: NextGen | C74: Complete | D74: ASM | E74: 46162 | F74: Carnesville Full Capital Ask | G74: =IF(ISBLANK(H74),"",_xlfn.XLOOKUP(H74,Info!A:A,Info!B:B)) -> 15 | H74: 46155 | I74: 0.625 | J74: 30 | K74: Karisa Sprague | L74: Kourtney Miller | M74: Decide | N74: Full approval for Carnesville | O74: Carnesville May ASM | P74: Jon Furner
A75: =IF(ISBLANK(E75),"",_xlfn.XLOOKUP(E75,Info!A:A,Info!B:B)) -> 16 | B75: NextGen | C75: Scheduled | D75: NextGen SteerCo | E75: 46162 | F75: Wallkill IRR & CapEx (Building Scenario's) | G75: =IF(ISBLANK(H75),"",_xlfn.XLOOKUP(H75,Info!A:A,Info!B:B)) -> 16 | H75: =E75-1 -> 46161 | I75: 0.16666667 | J75: 60 | K75: Lauren Siller | L75: Lauren Siller | M75: Decide | O75: 26_05_20 SteerCo Wallkill Scenarios.pptx
A76: =IF(ISBLANK(E76),"",_xlfn.XLOOKUP(E76,Info!A:A,Info!B:B)) -> 16 | B76: NextGen | C76: Scheduled | D76: NextGen SteerCo | E76: 46162 | F76: Burn Testing for NextGen (Decision Needed by June 1st) | G76: =IF(ISBLANK(H76),"",_xlfn.XLOOKUP(H76,Info!A:A,Info!B:B)) -> 16 | H76: 46162 | I76: 0.625 | J76: 10 | K76: Karen Slatton | L76: Kourtney Miller | M76: Decide | N76: Approved and will use Karisa OpEx | O76: 26_04_30 NextGen Burn Testing OpEx Required.pptx | P76: PK Sabherwal & Matt Termeer
A77: =IF(ISBLANK(E77),"",_xlfn.XLOOKUP(E77,Info!A:A,Info!B:B)) -> 16 | B77: NextGen | C77: Scheduled | D77: NextGen SteerCo | E77: 46162 | F77: Carnesville Incentives Funding: ~$1M OpEx needed for closing to secure ~$70M in incentives. | G77: =IF(ISBLANK(H77),"",_xlfn.XLOOKUP(H77,Info!A:A,Info!B:B)) -> 16 | H77: 46162 | I77: 0.5 | J77: 10 | K77: Greg Nunn | L77: Greg Nunn | M77: Decide | N77: Need feedback on where funding should come from
A78: =IF(ISBLANK(E78),"",_xlfn.XLOOKUP(E78,Info!A:A,Info!B:B)) -> #N/A | B78: NextGen | C78: Pending Scheduling | D78: NextGen SteerCo | E78: TBD | F78: Can we add TO/TMG to Wallkill | G78: =IF(ISBLANK(H78),"",_xlfn.XLOOKUP(H78,Info!A:A,Info!B:B)) | K78: Andrew Skinkle | L78: Andrew Skinkle | M78: Decide | P78: Adam Dunbar, Vik Gopalakrishnan, Jack Anderson, John Clinton
A79: =IF(ISBLANK(E79),"",_xlfn.XLOOKUP(E79,Info!A:A,Info!B:B)) -> #N/A | B79: NextGen | C79: Pending Scheduling | D79: NextGen SteerCo | E79: TBD | F79: BDR for MSP, DEN, SEA Sign-off (Confirm path to 150M capacity ramp by FY) | G79: =IF(ISBLANK(H79),"",_xlfn.XLOOKUP(H79,Info!A:A,Info!B:B)) | I79: 0.625 | J79: 30 | K79: Vijay Manoharan | L79: Vijay Manoharan | M79: Decide | N79: BRR Approval for MSP, DEN, & SEA | P79: Adam Dunbar, Vik Gopalakrishnan, Jack Anderson, John Clinton
A80: =IF(ISBLANK(E80),"",_xlfn.XLOOKUP(E80,Info!A:A,Info!B:B)) -> 16 | B80: NextGen | C80: Pending Scheduling | D80: NextGen SteerCo | E80: 46162 | F80: CPC DD Approval for Wallkill & Buckeye | G80: =IF(ISBLANK(H80),"",_xlfn.XLOOKUP(H80,Info!A:A,Info!B:B)) | K80: Kourtney Miller | L80: Kourtney Miller | M80: Decide | P80: Ellen Sloneker, Phil Herr
A81: =IF(ISBLANK(E81),"",_xlfn.XLOOKUP(E81,Info!A:A,Info!B:B)) -> #N/A | B81: NextGen | C81: Pending Scheduling | D81: NextGen SteerCo | E81: TBD | F81: Preliminary IRR for PHX, MCO, MSP, DEN, SEA | G81: =IF(ISBLANK(H81),"",_xlfn.XLOOKUP(H81,Info!A:A,Info!B:B)) | K81: Matt Termeer | M81: Decide | P81: Adam Dunbar, Vik Gopalakrishnan, Jack Anderson, John Clinton
A82: =IF(ISBLANK(E82),"",_xlfn.XLOOKUP(E82,Info!A:A,Info!B:B)) -> #N/A | B82: NextGen | C82: Pending Scheduling | D82: NextGen SteerCo | E82: TBD | F82: Reassess 450-mile centroid radius with impact to same day for MCO, MSP, DEN, SEA | G82: =IF(ISBLANK(H82),"",_xlfn.XLOOKUP(H82,Info!A:A,Info!B:B)) | K82: Vijay Manoharan | M82: Decide | P82: Adam Dunbar, Vik Gopalakrishnan, Jack Anderson, John Clinton
A83: =IF(ISBLANK(E83),"",_xlfn.XLOOKUP(E83,Info!A:A,Info!B:B)) -> #N/A | B83: NextGen | C83: Pending Scheduling | D83: NextGen SteerCo | E83: TBD | F83: Review Market Model Coverage with peak and off-peak (Stores, Depots, NextGen Conventional FC) | G83: =IF(ISBLANK(H83),"",_xlfn.XLOOKUP(H83,Info!A:A,Info!B:B)) | K83: Jack Anderson | M83: Decide | P83: Adam Dunbar, Vik Gopalakrishnan, Jack Anderson, John Clinton
A84: =IF(ISBLANK(E84),"",_xlfn.XLOOKUP(E84,Info!A:A,Info!B:B)) -> #N/A | B84: NextGen | C84: Pending Scheduling | D84: Offline | E84: TBD | F84: Site Selection Date Scheduling - MCO, MSP, SEA, DEN | G84: =IF(ISBLANK(H84),"",_xlfn.XLOOKUP(H84,Info!A:A,Info!B:B)) -> 13 | H84: 46143 | J84: 15 | K84: Kourtney Miller | L84: Kourtney Miller | M84: Decide | P84: Adam Dunbar
A85: =IF(ISBLANK(E85),"",_xlfn.XLOOKUP(E85,Info!A:A,Info!B:B)) -> 16 | B85: NextGen | C85: Complete | D85: Offline | E85: 46160 | F85: Carnesville ASM Dry Run | G85: =IF(ISBLANK(H85),"",_xlfn.XLOOKUP(H85,Info!A:A,Info!B:B)) -> 15 | H85: 46157 | I85: 0.5 | J85: 60 | K85: Karisa Sprague | L85: Kourtney Miller | M85: Review | N85: Feedback for Talking Points and FAQ prior to ASM | P85: Karisa Sprague
A86: =IF(ISBLANK(E86),"",_xlfn.XLOOKUP(E86,Info!A:A,Info!B:B)) -> #N/A | B86: NextGen | C86: Pending Scheduling | D86: NextGen SteerCo | E86: TBD | F86: Van/Sedan Delivery Flow Follow-up | G86: =IF(ISBLANK(H86),"",_xlfn.XLOOKUP(H86,Info!A:A,Info!B:B)) | J86: 30 | K86: Advaith Venkataraman / Andrew | L86: Advaith Venkataraman | M86: Decide | P86: Adam Dunbar, Jack Anderson
A87: =IF(ISBLANK(E87),"",_xlfn.XLOOKUP(E87,Info!A:A,Info!B:B)) | G87: =IF(ISBLANK(H87),"",_xlfn.XLOOKUP(H87,Info!A:A,Info!B:B))
A88: =IF(ISBLANK(E88),"",_xlfn.XLOOKUP(E88,Info!A:A,Info!B:B)) | G88: =IF(ISBLANK(H88),"",_xlfn.XLOOKUP(H88,Info!A:A,Info!B:B))
A89: =IF(ISBLANK(E89),"",_xlfn.XLOOKUP(E89,Info!A:A,Info!B:B)) | G89: =IF(ISBLANK(H89),"",_xlfn.XLOOKUP(H89,Info!A:A,Info!B:B))
A90: =IF(ISBLANK(E90),"",_xlfn.XLOOKUP(E90,Info!A:A,Info!B:B)) | G90: =IF(ISBLANK(H90),"",_xlfn.XLOOKUP(H90,Info!A:A,Info!B:B))
A91: =IF(ISBLANK(E91),"",_xlfn.XLOOKUP(E91,Info!A:A,Info!B:B)) | G91: =IF(ISBLANK(H91),"",_xlfn.XLOOKUP(H91,Info!A:A,Info!B:B))
A92: =IF(ISBLANK(E92),"",_xlfn.XLOOKUP(E92,Info!A:A,Info!B:B)) | G92: =IF(ISBLANK(H92),"",_xlfn.XLOOKUP(H92,Info!A:A,Info!B:B))
A93: =IF(ISBLANK(E93),"",_xlfn.XLOOKUP(E93,Info!A:A,Info!B:B)) | G93: =IF(ISBLANK(H93),"",_xlfn.XLOOKUP(H93,Info!A:A,Info!B:B))
A94: =IF(ISBLANK(E94),"",_xlfn.XLOOKUP(E94,Info!A:A,Info!B:B)) | G94: =IF(ISBLANK(H94),"",_xlfn.XLOOKUP(H94,Info!A:A,Info!B:B))
A95: =IF(ISBLANK(E95),"",_xlfn.XLOOKUP(E95,Info!A:A,Info!B:B)) | G95: =IF(ISBLANK(H95),"",_xlfn.XLOOKUP(H95,Info!A:A,Info!B:B))
A96: =IF(ISBLANK(E96),"",_xlfn.XLOOKUP(E96,Info!A:A,Info!B:B)) | G96: =IF(ISBLANK(H96),"",_xlfn.XLOOKUP(H96,Info!A:A,Info!B:B))
A97: =IF(ISBLANK(E97),"",_xlfn.XLOOKUP(E97,Info!A:A,Info!B:B)) | G97: =IF(ISBLANK(H97),"",_xlfn.XLOOKUP(H97,Info!A:A,Info!B:B))
A98: =IF(ISBLANK(E98),"",_xlfn.XLOOKUP(E98,Info!A:A,Info!B:B)) | G98: =IF(ISBLANK(H98),"",_xlfn.XLOOKUP(H98,Info!A:A,Info!B:B))
... A446: =IF(ISBLANK(E446),"",_xlfn.XLOOKUP(E446,Info!A:A,Info!B:B)) | G446: =IF(ISBLANK(H446),"",_xlfn.XLOOKUP(H446,Info!A:A,Info!B:B))

Sheet NG Timelines
A1: Program | B1: NextGen | C1: NextGen | D1: NextGen | E1: NextGen | F1: NextGen | G1: NextGen | H1: NextGen | Q1: Warning / Callout
A2: Node | B2: Southeast | C2: West | D2: Northeast | E2: Southeast | F2: Upper Midwest | G2: Mountain West | H2: Pacific Northwest | Q2: Placeholder until real date/information is updated
A3: Location | B3: Carnesville, GA | C3: Buckeye, AZ | D3: Wallkill, NY | E3: Orlando, FL | F3: Minneapolis, MN | G3: Denver, CO | H3: Seattle, WA | Q3: Project Start
A4: State | B4: GA | C4: AZ | D4: NY | E4: FL | F4: MN | G4: CO | H4: WA
A5: FC Number | B5: 4843 | C5: TBD | D5: 7028 | E5: TBD | F5: TBD | G5: TBD | H5: TBD
A6: Airport Code | B6: ATL5 | C6: TBD | D6: LGA1 | E6: MCO? | F6: MSP? | G6: DEN? | H6: SEA?
A7: BDR Sign-off | B7: 45923 | C7: 46100 | D7: 46100 | E7: 46128 | F7: 46135 | G7: 46135 | H7: 46135
A8: Design and Construction
A9: Test Fits Complete | E9: 46164 | F9: 46164 | G9: TBD | H9: TBD
A10: Due Diligence: Site Selection | B10: 45792 | C10: 45979 | D10: 45979 | E10: 46128 | F10: 46128 | G10: 46128 | H10: 46128
A11: Due Diligence 30% Work Ahead | B11: 45792 | C11: 45979 | D11: 45860 | E11: TBD | F11: TBD | G11: TBD | H11: TBD
A12: Due Diligence: 30% Design | B12: 45855 | C12: 46080 | D12: 45993 | E12: TBD | F12: TBD | G12: TBD | H12: TBD
A13: Due Diligence: 60% Design | B13: 45971 | C13: 46080 | D13: 46080 | E13: TBD | F13: TBD | G13: TBD | H13: TBD
A14: Due Diligence: 90% Design | B14: 45971 | C14: 46253 | D14: 46164 | E14: TBD | F14: TBD | G14: TBD | H14: TBD
A15: Due Diligence: CA Design | B15: 45971 | C15: 46253 | D15: 46253 | E15: TBD | F15: TBD | G15: TBD | H15: TBD
A16: Site Selected | B16: 45800 | C16: 46114 | D16: 45952 | E16: 46248 | F16: 46248 | G16: 46283 | H16: 46283
A17: Start of Design | B17: 45859 | C17: 46083 | D17: 45992
A18: 30% Design Complete | B18: 45958 | C18: 46199 | D18: 46080 | E18: 46367 | F18: 46269 | G18: 46395 | H18: 46395
A19: 30% ROM Pricing | B19: 45982 | C19: 46227 | D19: 46115 | E19: 46416 | F19: 46416 | G19: 46430 | H19: 46430
A20: 60% Design Complete | B20: 46087 | C20: 46269 | D20: 46171 | E20: 46451 | F20: 46451 | G20: 46465 | H20: 46465
A21: 60% ROM Pricing | B21: 46122 | C21: 46297 | D21: 46206 | E21: 46486 | F21: 46486 | G21: 46500 | H21: 46500
A22: 90% Design Complete | B22: 46143 | C22: 46339 | D22: 46241 | E22: 46521 | F22: 46521 | G22: 46535 | H22: 46535
A23: Out to Permit | B23: 46153 | C23: 46370 | D23: 46132 | E23: 46531 | F23: 46531 | G23: 46545 | H23: 46545
A24: Permit Complete | B24: 46248 | C24: 46465 | D24: 46780 | E24: 46731 | F24: 46731 | G24: 46913 | H24: 46913
A25: Construction Start | B25: 46272 | C25: 46496 | D25: 46811 | E25: 46762 | F25: 46762 | G25: 46944 | H25: 46944
A26: Construction Substantial Completion | B26: 46878 | C26: 47102 | D26: 47417 | E26: 47375 | F26: 47375 | G26: 47543 | H26: 47543
A27: Phase 1 Go-live | B27: 47056 | C27: 47291 | D27: 47616 | E27: 47553 | F27: 47553 | G27: 47735 | H27: 47735
A28: Phase 2 Go-live | B28: 47245 | C28: 47455 | D28: 47791 | E28: 47728 | F28: 47728 | G28: 47917 | H28: 47917
A29: Go-Live FY | B29: FY29 | C29: FY30 | D29: FY31 | E29: FY31 | F29: FY31 | G29: FY31 | H29: FY31
A30: FY Capacity Added | B30: FY29 | C30: FY30 | D30: FY31 | E30: FY31 | F30: FY31 | G30: FY31 | H30: FY31
A31: Governance
A32: Steer Co | B32: 46107 | C32: 46307 | D32: 46188 | E32: TBD | F32: TBD | G32: TBD | H32: TBD
A33: Vertical Start-Up | B33: 46100 | C33: 46317 | D33: 46198 | E33: TBD | F33: TBD | G33: TBD | H33: TBD
A34: SCDB Turn in | B34: 46108 | C34: 46318 | D34: 46213 | E34: TBD | F34: TBD | G34: TBD | H34: TBD
A35: SCDB | B35: 46111 | C35: 46321 | D35: 46216 | E35: TBD | F35: TBD | G35: TBD | H35: TBD
A36: RLM Turn-In | B36: 46107 | C36: 46309 | D36: 46211 | E36: TBD | F36: TBD | G36: TBD | H36: TBD
A37: RLM | B37: 46114 | C37: 46317 | D37: 46217 | E37: TBD | F37: TBD | G37: TBD | H37: TBD
A38: REC Turn-In | B38: 46122 | C38: 46323 | D38: 46224 | E38: TBD | F38: TBD | G38: TBD | H38: TBD
A39: REC | B39: 46127 | C39: 46330 | D39: 46231 | E39: TBD | F39: TBD | G39: TBD | H39: TBD
A40: CFO Turn-In | B40: 46139 | C40: 46341 | D40: 46230 | E40: TBD | F40: TBD | G40: TBD | H40: TBD
A41: CFO Review | B41: 46146 | C41: 46345 | D41: 46237 | E41: TBD | F41: TBD | G41: TBD | H41: TBD
A42: CPC Turn-In | B42: 46147 | C42: 46345 | D42: 46238 | E42: TBD | F42: TBD | G42: TBD | H42: TBD
A43: CPC | B43: 46153 | C43: 46358 | D43: 46244 | E43: TBD | F43: TBD | G43: TBD | H43: TBD
A44: MSM Turn-In | B44: 46148
A45: MSM | B45: 46154
A46: ASM Turn-In | B46: 46154 | C46: 46357 | D46: 46245 | E46: TBD | F46: TBD | G46: TBD | H46: TBD
A47: ASM | B47: 46162 | C47: 46366 | D47: 46253 | E47: 46555 | F47: 46555 | G47: 46583 | H47: 46583
A48: Engineering Design and Install
A49: 30 % Design - ENG | B49: =B18-30 -> 45928 | C49: =C18-30 -> 46169 | D49: =D18-30 -> 46050 | E49: =E18-30 -> 46337 | F49: =F18-30 -> 46239 | G49: =G18-30 -> 46365 | H49: =H18-30 -> 46365
A50: 60% Design -ENG | B50: =B20-30 -> 46057 | C50: =C20-30 -> 46239 | D50: =D20-30 -> 46141 | E50: =E20-30 -> 46421 | F50: =F20-30 -> 46421 | G50: =G20-30 -> 46435 | H50: =H20-30 -> 46435
A51: 90% Design - ENG | B51: =B22-30 -> 46113 | C51: =C22-30 -> 46309 | D51: =D22-30 -> 46211 | E51: =E22-30 -> 46491 | F51: =F22-30 -> 46491 | G51: =G22-30 -> 46505 | H51: =H22-30 -> 46505
A52: KNAPP Signed SOW | B52: =B47+7 -> 46169 | C52: =C47+7 -> 46373 | D52: =D47+7 -> 46260 | E52: =E47+7 -> 46562 | F52: =F47+7 -> 46562 | G52: =G47+7 -> 46590 | H52: =H47+7 -> 46590
A53: KNAPP start of Install (Start) | B53: =B27-517 -> 46539 | C53: =C27-517 -> 46774 | D53: =D27-517 -> 47099 | E53: =E27-517 -> 47036 | F53: =F27-517 -> 47036 | G53: =G27-517 -> 47218 | H53: =H27-517 -> 47218
A54: Phase 1 Commissioning - (Start) | B54: TBD | C54: TBD | D54: TBD | E54: TBD | F54: TBD | G54: TBD | H54: TBD
A55: FAT, End to End Testing, Financial Validation (Start) | B55: TBD | C55: TBD | D55: TBD | E55: TBD | F55: TBD | G55: TBD | H55: TBD
A56: Additional Key Dates
A57: Business Case Intake Open | B57: 46097 | C57: TBD | D57: =D58-14 -> 46153 | E57: TBD | F57: TBD | G57: TBD | H57: TBD
A58: Business Case Intake Closed | B58: 46118 | C58: TBD | D58: =D32-21 -> 46167 | E58: TBD | F58: TBD | G58: TBD | H58: TBD
A59: Business Case Complete | B59: 46122 | C59: TBD | D59: 46181 | E59: TBD | F59: TBD | G59: TBD | H59: TBD
A60: Incentives Secured | B60: TBD | C60: TBD | D60: TBD | E60: TBD | F60: TBD | G60: TBD | H60: TBD
A61: REC Dry Run | B61: 46121 | C61: TBD | D61: TBD | E61: TBD | F61: TBD | G61: TBD | H61: TBD
A62: CPC Dry Run | B62: 46143 | C62: TBD | D62: TBD | E62: TBD | F62: TBD | G62: TBD | H62: TBD
A63: ASM Dry Run | B63: 46160 | C63: TBD | D63: TBD | E63: TBD | F63: TBD | G63: TBD | H63: TBD
A64: Moratorium Termination | B64: N/A | C64: N/A | D64: 46171 | E64: N/A | F64: N/A | G64: N/A | H64: N/A
A65: Talking Points & FAQ Updated | B65: 46141 | C65: TBD | D65: TBD | E65: TBD | F65: TBD | G65: TBD | H65: TBD
A66: Town Board Review Height Variance | D66: 46171
A67: Zoning Board Review Heigh Variance | D67: 46185
A68: Real Estate Milestones
A69: Site Selection Trip | B69: 45800 | C69: 46113 | D69: 45983 | E69: 46231 | F69: 46259 | G69: TBD | H69: TBD
A70: PSA Signing | C70: 46231
A71: ASM for Land Purchase | C71: =D47 -> 46253
A72: Land Purchase (Cash Flow) | B72: 46204

Sheet NG Budget
A1: Project # | B1: LX Number | C1: SAP Project # | D1: Building Type | E1: Brief Scope of Work | F1: Stage | G1: FC Name | H1: DC | I1: Location | J1: Node | K1: Name | N1: Budget | O1: Actualized | P1: Open Commits | Q1: Assigned | R1: % of Assigned | S1: Notes
A2: 17 | B2: 90256.1000 | C2: USDC-000297 | D2: Next Gen | E2: New Build | F2: Pre-ASM | G2: DOU | H2: TBD | I2: Doulas, MA | J2: WMUS.SG.LOG.ASM | K2: =CONCATENATE(C2,"|",G2,"|",H2) -> USDC-000297|DOU|TBD | M2: 297 | N2: 643300 | O2: 432505 | P2: 144708 | Q2: =O2+P2 -> 577213 | R2: =Q2/N2 -> 0.89726877 | S2: On Hold
A3: 17 | B3: 90235.1000 | C3: USDC-000298 | D3: Next Gen | E3: New Build | F3: Pre-ASM | G3: ATL5 | H3: 4844 | I3: Carnesville, GA | J3: WMUS.SG.LOG.ASM | K3: =CONCATENATE(C3,"|",G3,"|",H3) -> USDC-000298|ATL5|4844 | M3: 298 | N3: 195514000 | O3: 100633569 | P3: 22153648 | Q3: =O3+P3 -> 122787217 | R3: =Q3/N3 -> 0.62802263 | S3: Nov ASM Approved Budget Loaded
A4: 17 | B4: 90367.1000 | C4: USDC-000302 | D4: Next Gen | E4: New Build | F4: Pre-ASM | G4: LAS | H4: TBD | I4: Las Vegas, NV | J4: WMUS.SG.LOG.EASM | K4: =CONCATENATE(C4,"|",G4,"|",H4) -> USDC-000302|LAS|TBD | M4: 302 | N4: 2206000 | O4: 1586608 | P4: 174892 | Q4: =O4+P4 -> 1761500 | R4: =Q4/N4 -> 0.79850408 | S4: On Hold
B5: 90536.1000 | C5: USDC-000308 | D5: Next Gen | E5: New Build | F5: Pre-ASM | G5: LGA1 | H5: 7028 | I5: Wallkill, NY | J5: WMUS.SG.LOG.EASM | K5: =CONCATENATE(C5,"|",G5,"|",H5) -> USDC-000308|LGA1|7028 | M5: 308 | N5: 5000000 | O5: 1364948 | P5: 2190302 | Q5: =O5+P5 -> 3555250 | R5: =Q5/N5 -> 0.71105
B6: 90537.1000 | C6: USDC-000309 | D6: Next Gen | E6: New Build | F6: Pre-ASM | G6: PHX3 | H6: TBD | I6: Buckeye, AZ | J6: WMUS.SG.LOG.EASM | K6: =CONCATENATE(C6,"|",G6,"|",H6) -> USDC-000309|PHX3|TBD | M6: 309 | N6: 5000000 | O6: 0 | P6: 2018000 | Q6: =O6+P6 -> 2018000 | R6: =Q6/N6 -> 0.4036
B7: 8654.1000 | C7: USDC-000311 | D7: Next Gen | E7: New Build | F7: Pre-ASM | G7: DEN | H7: TBD | I7: Denver, CO | J7: WMUS.SG.LOG.EASM | K7: =CONCATENATE(C7,"|",G7,"|",H7) -> USDC-000311|DEN|TBD | Q7: =O7+P7 -> 0 | S7: Land bank not viable for NextGen
B8: 90591.1000 | C8: USDC-000312 | D8: Next Gen | E8: New Build | F8: Pre-ASM | G8: MCO | H8: TBD | I8: Orlando, FL | J8: WMUS.SG.LOG.EASM | K8: =CONCATENATE(C8,"|",G8,"|",H8) -> USDC-000312|MCO|TBD | N8: 500000 | O8: 0 | P8: 0 | Q8: =O8+P8 -> 0 | R8: =Q8/N8 -> 0 | S8: 4/16: $500K funded for campus site selection
B9: 90593.1000 | C9: USDC-000313 | D9: Next Gen | E9: New Build | F9: Pre-ASM | G9: SEA | H9: TBD | I9: Seattle, WA | J9: WMUS.SG.LOG.EASM | K9: =CONCATENATE(C9,"|",G9,"|",H9) -> USDC-000313|SEA|TBD | N9: 500000 | O9: 0 | P9: 0 | Q9: =O9+P9 -> 0 | R9: =Q9/N9 -> 0 | S9: 4/16: $500K funded for campus site selection
B10: 90592.1000 | C10: USDC-000314 | D10: Next Gen | E10: New Build | F10: Pre-ASM | G10: MSP | H10: TBD | I10: Minneapolis, MN | J10: WMUS.SG.LOG.EASM | K10: =CONCATENATE(C10,"|",G10,"|",H10) -> USDC-000314|MSP|TBD | N10: 500000 | O10: 0 | P10: 58000 | Q10: =O10+P10 -> 58000 | R10: =Q10/N10 -> 0.116 | S10: 4/16: $500K funded for campus site selection
B11: 90915.1000 | C11: USDC-000317 | D11: Next Gen | E11: New Build | F11: Pre-ASM | G11: DEN | H11: TBD | I11: Denver, CO | J11: WMUS.SG.LOG.EASM | K11: =CONCATENATE(C11,"|",G11,"|",H11) -> USDC-000317|DEN|TBD | N11: 500000 | O11: 0 | P11: 0 | Q11: =O11+P11 -> 0 | R11: =Q11/N11 -> 0 | S11: 4/16: $500K funded for campus site selection

Sheet Automation Launch Dates
A1: Scope | B1: NextGen Greenfield | C1: NextGen Aisle Expansion | D1: NextGen Aisle Expansion | E1: NextGen Aisle Expansion | F1: NextGen Aisle Expansion | G1: NextGen Greenfield | H1: NextGen Greenfield | I1: NextGen Greenfield | J1: NextGen Greenfield | K1: NextGen Greenfield | L1: NextGen Greenfield | M1: NextGen Greenfield | N1: Non-Sort New Site | O1: Non-Sort New Site | P1: Non-Sort New Site | Q1: Non-Sort New Site | R1: Non-Sort New Site | S1: Non-Sort New Site | T1: LAX2 ICC Expansion | U1: IND1 ICC + Two-Tier
A2: Sites | B2: Stockton, CA | C2: McCordsville, IN | D2: Joliet, IL | E2: Lancaster, TX | F2: Green Castle, PA | G2: Carnesville, GA | H2: Buckeye, AZ | I2: Wallkill, NY | J2: Orlando, FL | K2: Minneapolis, MN | L2: Denver, CO | M2: Seattle, WA | N2: Pheonix, AZ | O2: Charlotte, NC | P2: Indianapolis, IN | Q2: Shoemakersville, PA | R2: East Hartford, CT | S2: Lebanon, OH | T2: Chino, CA | U2: Indianapolis, IN
A3: Status | B3: In Flight | C3: In Flight | D3: In Flight | E3: In Flight | F3: In Flight | G3: May ASM | H3: Dec ASM | I3: Aug ASM | J3: Due Diligence In Design | K3: Due Diligence In Design | L3: Due Diligence In Design | M3: Due Diligence In Design | N3: In Flight | O3: In Flight | P3: In Flight | Q3: August ASM | R3: August ASM | S3: August ASM | T3: In Flight | U3: In Flight
A4: Phase 1 Go-live | B4: 46258 | C4: 46293 | D4: 46273 | E4: 46573 | F4: 45457 | G4: 10/30/28 (FY29) | H4: 6/22/2029 (FY30) | I4: 5/12/30 (FY31) | J4: 11/19/29 (FY30) | K4: 11/19/29 (FY30) | L4: 5/13/30 (FY31) | M4: 5/13/30 (FY31) | N4: 4/20/2027 (FY28) | O4: 5/20/2027 (FY28) | P4: 4/20/2027 (FY28)
A5: Phase 2 Go-live | C5: 46596 | D5: 46520 | G5: 5/7/29 (FY30) | H5: 12/3/2029 (FY30) | I5: 11/4/30 (FY31) | J5: 5/13/30 (FY31) | K5: 5/13/30 (FY31) | L5: 11/11/30 (FY31) | M5: 11/11/30 (FY31)
A7: Phase 1 Go-live | B7: FY27 3Q | C7: FY27 3Q | D7: FY27 3Q | E7: FY28 2Q | F7: FY28 2Q | G7: FY29 3Q | H7: FY30 Q2 | I7: FY31 Q2 | J7: FY31 Q1 | K7: FY31 Q1 | L7: FY31 Q3 | M7: FY31 Q3 | N7: FY28 Q1 | O7: FY28 Q2 | P7: FY28 Q1 | Q7: FY29 Q1 | R7: FY29 Q1 | S7: FY29 Q1 | T7: FY27 Q3 | U7: FY27 Q3
A8: Phase 2 Go-live | B8: FY28 2Q | C8: FY28 3Q | D8: FY28 2Q | G8: FY30 2Q | H8: FY30 Q4 | I8: FY31 Q4 | J8: FY31 Q3 | K8: FY31 Q3 | L8: FY32 Q1 | M8: FY32 Q1 | N8: FY28 Q1 | T8: FY28 Q1 | U8: FY28 Q2

Sheet Info
A1: Date | B1: Walmart Week | I1: Month | J1: Quarter | M1: Month | N1: Quarter
A2: 46054 | B2: 1 | I2: Feb | J2: 1 | M2: Feb | N2: 1
A3: 46055 | B3: 1 | I3: Mar | J3: 1 | M3: Mar
A4: 46056 | B4: 1 | I4: Apr | J4: 1 | M4: Apr
A5: 46057 | B5: 1 | I5: May | J5: 2 | M5: May | N5: 2
A6: 46058 | B6: 1 | I6: Jun | J6: 2 | M6: Jun
A7: 46059 | B7: 1 | I7: Jul | J7: 2 | M7: Jul
A8: 46060 | B8: 2 | I8: Aug | J8: 3 | M8: Aug | N8: 3
A9: 46061 | B9: 2 | I9: Sep | J9: 3 | M9: Sep
A10: 46062 | B10: 2 | I10: Oct | J10: 3 | M10: Oct
A11: 46063 | B11: 2 | I11: Nov | J11: 4 | M11: Nov | N11: 4
A12: 46064 | B12: 2 | I12: Dec | J12: 4 | M12: Dec
A13: 46065 | B13: 2 | I13: Jan | J13: 4 | M13: Jan
A14: 46066 | B14: 2
A15: 46067 | B15: =B8+1 -> 3
A16: 46068 | B16: =B9+1 -> 3
A17: 46069 | B17: =B10+1 -> 3
A18: 46070 | B18: =B11+1 -> 3
A19: 46071 | B19: =B12+1 -> 3
A20: 46072 | B20: =B13+1 -> 3
A21: 46073 | B21: =B14+1 -> 3
A22: 46074 | B22: =B15+1 -> 4
A23: 46075 | B23: =B16+1 -> 4
A24: 46076 | B24: =B17+1 -> 4
A25: 46077 | B25: =B18+1 -> 4
A26: 46078 | B26: =B19+1 -> 4
... A366: 46418 | B366: =B359+1 -> 53
